pytorch_optimize/__init__.py
pytorch_optimize/evaluator.py
pytorch_optimize/model.py
pytorch_optimize/objective.py
pytorch_optimize/optimizer.py
pytorch_optimize/scaler.py
pytorch_optimize-0.0.1.dist-info/LICENSE
pytorch_optimize-0.0.1.dist-info/METADATA
pytorch_optimize-0.0.1.dist-info/WHEEL
pytorch_optimize-0.0.1.dist-info/top_level.txt
pytorch_optimize-0.0.1.dist-info/RECORD
