Metadata-Version: 2.1
Name: pytorch-optimize
Version: 0.0.1
Summary: Package to train pytorch models for non-differentiable objectives
Home-page: https://github.com/rajcscw/pytorch-optimize
Author: Rajkumar Ramamurthy
Author-email: raj1514@gmail.com
License: UNKNOWN
Platform: UNKNOWN
Requires-Python: >=3.7
Requires-Dist: numpy
Requires-Dist: torch
Requires-Dist: torchvision
Requires-Dist: tqdm
Requires-Dist: pycodestyle
Requires-Dist: pytest
Requires-Dist: sklearn
